{
  "heading": "2. CuTe DSL Compilation Flow: Meta-Stage to Object-Stage",
  "level": 2,
  "content": "CuTe DSL bridges Python and GPU hardware through a three-stage pipeline.\n\n[![../../../../_images/dsl_modes.png](../../../../_images/dsl_modes.png)](../../../../_images/dsl_modes.png)\n\nFigure 1 *Left*: tracing mode records only the path that executed.\n*Right*: preprocessor mode emits structured intermediate representation (IR) for every branch and loop\nbefore tracing the arithmetic.[#](#id1 \"Link to this image\")\n\nThe default CuTe DSL compilation pipeline (mode 2): Python source flows through AST preprocessing\nand interpreter-driven tracing to produce intermediate representation (IR), which is then lowered and\ncompiled to device code.\n\n**Stage 1: Pre-Staging (Python AST)**\n\nBefore any code executes, the AST preprocessor rewrites the decorated function.\nIt inserts *callbacks* around control-flow constructs\u2014loops, branches, and\nfunction boundaries\u2014so that program structure is captured explicitly rather than\nlost during execution.\n\n**Stage 2: Meta-Stage (Python Interpreter)**\n\nThe rewritten function runs in the Python interpreter with proxy tensor\narguments. As execution proceeds:\n\n* Callbacks fire at control-flow boundaries, emitting structured intermediate representation (IR) (loops,\n  branches, etc.).\n* Tensor operations are traced: each operator invocation records the\n  corresponding operation.\n* Compile-time constants are *partially evaluated*\u2014values known at JIT time\n  fold directly into the intermediate representation (IR), enabling aggressive specialization.\n\nThe result is a complete representation of the kernel, with both high-level\nstructure and low-level arithmetic intact.\n\n**Stage 3: Object-Stage (Compiler Backend)**\n\nThe internal representation passes through a lowering pipeline:\n\n1. High-level operations are progressively lowered toward hardware-specific\n   representations.\n2. Optimization passes (tiling, vectorization, memory promotion) reshape the\n   code for the target architecture.\n3. The final code is translated to PTX/SASS (for NVIDIA GPUs) and assembled\n   into a device binary.\n\nAt runtime, the compiled kernel is loaded and launched on the accelerator.",
  "source_page": "cute_dsl_general/dsl_code_generation.html",
  "source_url": "https://docs.nvidia.com/cutlass/latest/media/docs/pythonDSL/cute_dsl_general/dsl_code_generation.html",
  "page_title": "End"
}