{
  "heading": "Source: cutlass.utils.blockscaled_layout",
  "module": "cutlass.utils.blockscaled_layout",
  "file_path": "utils/blockscaled_layout.py",
  "content": "# Module: `cutlass.utils.blockscaled_layout`\n\nFile: `utils/blockscaled_layout.py`\n\n\n---\n\n## class `BlockScaledBasicChunk`\n\n@dataclass(frozen=True)\nThe basic scale factor atom layout decided by tcgen05 BlockScaled MMA Ops.\n\nThis class represents the fixed layout pattern for scale factors used in\ntcgen05 BlockScaled MMA Ops. The layout is determined by the\ninstruction specification and cannot be modified.\nSee `PTX documentation <https://docs.nvidia.com/cuda/parallel-thread-execution/#tcgen05-mma-scale-factor-a-layout-1x>`.\n\n---\n\n## `tile_atom_to_shape_SF(Shape: cute.Shape, sf_vec_size: int) -> cute.Layout`\n\n@dsl_user_op\nA helper function to get dynamic SFA/SFB layout by filling dynamic A/B shape to the scale factor atom layout.\n\n:param Shape: The shape of the A/B tensor\n:param sf_vec_size: Scale factor vector size\n\n:return: The layout of the SFA/SFB tensor\n:rtype: cute.Layout\n\n---\n\n## `make_smem_layout_sf(tile_shape: cute.Tile, sf_vec_size: int, num_stages: int) -> cute.Layout`\n\n@dsl_user_op\nA helper function to get dynamic SFA/SFB layout by filling dynamic A/B shape to the scale factor atom layout.\n\n:param Shape: The shape of the A/B tensor\n:param sf_vec_size: Scale factor vector size\n:param num_stages: Number of stages\n\n:return: The layout of the SFA/SFB tensor\n:rtype: cute.Layout\n\n---\n\n## `make_smem_layout_sfa(tiled_mma: cute.TiledMma, mma_tiler_mnk: cute.Tile, sf_vec_size: int, num_stages: int) -> cute.Layout`\n\n@dsl_user_op\nMake smem layout for SFA based on:\n\n1. BlockScaledBasicChunk\n2. MMA tiler shape\n3. Scale factor vector size\n4. Number of stages\n\n:param tiled_mma: The tiled MMA\n:type tiled_mma: cute.TiledMma\n:param mma_tiler_mnk: The mma tiler shape\n:type mma_tiler_mnk: cute.Tile\n:param sf_vec_size: The scale factor vector size\n:type sf_vec_size: int\n:param num_stages: The number of stages\n:type num_stages: int\n\n:return: Smem layout for SFA\n:rtype: cute.Layout\n\n---\n\n## `make_smem_layout_sfb(tiled_mma: cute.TiledMma, mma_tiler_mnk: cute.Tile, sf_vec_size: int, num_stages: int) -> cute.Layout`\n\n@dsl_user_op\nMake smem layout for SFB based on:\n\n1. BlockScaledBasicChunk\n2. MMA tiler shape\n3. Scale factor vector size\n4. Number of stages\n\n:param tiled_mma: The tiled MMA\n:type tiled_mma: cute.TiledMma\n:param mma_tiler_mnk: The mma tiler shape\n:type mma_tiler_mnk: cute.Tile\n:param sf_vec_size: The scale factor vector size\n:type sf_vec_size: int\n:param num_stages: The number of stages\n:type num_stages: int\n\n:return: Smem layout for SFA\n:rtype: cute.Layout\n\n---\n\n## `sm120_make_smem_layout_sfa(tiled_mma: cute.TiledMma, tile_shape_mnk: cute.Tile, sf_vec_size: int, num_stages: int) -> cute.Layout`\n\n@dsl_user_op\nMake smem layout for SFA based on:\n1. BlockScaledBasicChunk\n2. MMA tiler shape\n3. Scale factor vector size\n4. Number of stages\n\n:param tiled_mma: The tiled MMA\n:type tiled_mma: cute.TiledMma\n:param mma_tiler_mnk: The mma tiler shape\n:type mma_tiler_mnk: cute.Tile\n:param sf_vec_size: The scale factor vector size\n:type sf_vec_size: int\n:param num_stages: The number of stages\n:type num_stages: int\n\n:return: Smem layout for SFA\n:rtype: cute.Layout\n\n---\n\n## `sm120_make_smem_layout_sfb(tiled_mma: cute.TiledMma, tile_shape_mnk: cute.Tile, sf_vec_size: int, num_stages: int) -> cute.Layout`\n\n@dsl_user_op\nMake smem layout for SFB based on:\n1. BlockScaledBasicChunk\n2. MMA tiler shape\n3. Scale factor vector size\n4. Number of stages\n\n:param tiled_mma: The tiled MMA\n:type tiled_mma: cute.TiledMma\n:param mma_tiler_mnk: The mma tiler shape\n:type mma_tiler_mnk: cute.Tile\n:param sf_vec_size: The scale factor vector size\n:type sf_vec_size: int\n:param num_stages: The number of stages\n:type num_stages: int\n\n:return: Smem layout for SFA\n:rtype: cute.Layout\n\n---\n\n## `make_tmem_layout_sfa(tiled_mma: cute.TiledMma, mma_tiler_mnk: cute.Tile, sf_vec_size: int, smem_layout: cute.Layout) -> cute.Layout`\n\n@dsl_user_op\nMake tmem layout for SFA based on:\n\n1. SFA smem layout per stage\n2. Cta tile shape m\n3. tiled MMA atom thr size\n4. Scale factor vector size\n\n:param tiled_mma: The tiled MMA\n:type tiled_mma: cute.TiledMma\n:param mma_tiler_mnk: The mma tiler shape\n:type mma_tiler_mnk: cute.Tile\n:param sf_vec_size: The scale factor vector size\n:type sf_vec_size: int\n:param smem_layout: The smem layout of SFA per stage\n:type smem_layout: cute.Layout\n\n:return: TMEM layout for SFA\n:rtype: cute.Layout\n\n---\n\n## `make_tmem_layout_sfb(tiled_mma: cute.TiledMma, mma_tiler_mnk: cute.Tile, sf_vec_size: int, smem_layout: cute.Layout) -> cute.Layout`\n\n@dsl_user_op\nMake tmem layout for SFB based on:\n\n1. SFB smem layout per stage\n2. Cta tile shape m\n3. tiled MMA atom thr size\n4. Scale factor vector size\n\n:param tiled_mma: The tiled MMA\n:type tiled_mma: cute.TiledMma\n:param mma_tiler_mnk: The mma tiler shape\n:type mma_tiler_mnk: cute.Tile\n:param sf_vec_size: The scale factor vector size\n:type sf_vec_size: int\n:param smem_layout: The smem layout of SFB per stage\n:type smem_layout: cute.Layout\n\n:return: TMEM layout for SFB\n:rtype: cute.Layout\n\n---\n\n## `__post_init__(self) -> None`\n\n\n\n---\n\n## `layout(self) -> cute.Layout`\n\n@property\nGet the layout for this block scaled chunk.\n\n:return: The layout representing the scale factor atom\n:rtype: cute.Layout",
  "symbols": [
    "BlockScaledBasicChunk",
    "tile_atom_to_shape_SF",
    "make_smem_layout_sf",
    "make_smem_layout_sfa",
    "make_smem_layout_sfb",
    "sm120_make_smem_layout_sfa",
    "sm120_make_smem_layout_sfb",
    "make_tmem_layout_sfa",
    "make_tmem_layout_sfb",
    "__post_init__",
    "layout"
  ],
  "source_code": "# SPDX-FileCopyrightText: Copyright (c) 2025 - 2026 NVIDIA CORPORATION & AFFILIATES. All rights reserved.\n# SPDX-License-Identifier: LicenseRef-NvidiaProprietary\n#\n# Use of this software is governed by the terms and conditions of the\n# NVIDIA End User License Agreement (EULA), available at:\n# https://docs.nvidia.com/cutlass/media/docs/pythonDSL/license.html\n#\n# Any use, reproduction, disclosure, or distribution of this software\n# and related documentation outside the scope permitted by the EULA\n# is strictly prohibited.\n\nfrom dataclasses import dataclass, field\n\nfrom cutlass.cutlass_dsl import dsl_user_op\n\nimport cutlass.cute as cute\nfrom cutlass.cute.nvgpu.tcgen05 import OperandMajorMode\n\nimport cutlass._mlir.dialects.cute as _cute_ir\nimport cutlass._mlir.dialects.cute_nvgpu as _cute_nvgpu_ir\n\n\n@dataclass(frozen=True)\nclass BlockScaledBasicChunk:\n    \"\"\"\n    The basic scale factor atom layout decided by tcgen05 BlockScaled MMA Ops.\n\n    This class represents the fixed layout pattern for scale factors used in\n    tcgen05 BlockScaled MMA Ops. The layout is determined by the\n    instruction specification and cannot be modified.\n    See `PTX documentation <https://docs.nvidia.com/cuda/parallel-thread-execution/#tcgen05-mma-scale-factor-a-layout-1x>`.\n    \"\"\"\n\n    sf_vec_size: int\n    major_mode: OperandMajorMode = OperandMajorMode.K\n    _layout: cute.Layout = field(init=False, repr=False)\n\n    def __post_init__(self) -> None:\n        if self.major_mode == OperandMajorMode.K:\n            # K-major layout: (AtomMN, AtomK)\n            atom_shape = ((32, 4), (self.sf_vec_size, 4))\n            atom_stride = ((16, 4), (0, 1))\n        else:\n            # MN-major layout: (AtomK, AtomMN)\n            atom_shape = ((self.sf_vec_size, 4), (32, 4))\n            atom_stride = ((0, 1), (16, 4))\n\n        object.__setattr__(\n            self, \"_layout\", cute.make_layout(atom_shape, stride=atom_stride)\n        )\n\n    @property\n    def layout(self) -> cute.Layout:\n        \"\"\"\n        Get the layout for this block scaled chunk.\n\n        :return: The layout representing the scale factor atom\n        :rtype: cute.Layout\n        \"\"\"\n        return self._layout\n\n\n@dsl_user_op\ndef tile_atom_to_shape_SF(\n    Shape: cute.Shape,\n    sf_vec_size: int,\n    *,\n    loc=None,\n    ip=None,\n) -> cute.Layout:\n    \"\"\"\n    A helper function to get dynamic SFA/SFB layout by filling dynamic A/B shape to the scale factor atom layout.\n\n    :param Shape: The shape of the A/B tensor\n    :param sf_vec_size: Scale factor vector size\n\n    :return: The layout of the SFA/SFB tensor\n    :rtype: cute.Layout\n    \"\"\"\n    # ((Atom_MN, Rest_MN),(Atom_K, Rest_K),RestL)\n    sf_layout = cute.tile_to_shape(\n        BlockScaledBasicChunk(sf_vec_size).layout, Shape, (2, 1, 3)\n    )\n    return sf_layout\n\n\n@dsl_user_op\ndef make_smem_layout_sf(\n    tile_shape: cute.Tile,\n    sf_vec_size: int,\n    num_stages: int,\n    *,\n    loc=None,\n    ip=None,\n) -> cute.Layout:\n    \"\"\"\n    A helper function to get dynamic SFA/SFB layout by filling dynamic A/B shape to the scale factor atom layout.\n\n    :param Shape: The shape of the A/B tensor\n    :param sf_vec_size: Scale factor vector size\n    :param num_stages: Number of stages\n\n    :return: The layout of the SFA/SFB tensor\n    :rtype: cute.Layout\n    \"\"\"\n\n    smem_layout = cute.tile_to_shape(\n        BlockScaledBasicChunk(sf_vec_size).layout, tile_shape, (2, 1)\n    )\n    smem_layout_staged = cute.append(\n        smem_layout,\n        cute.make_layout(\n            num_stages, stride=cute.cosize(cute.filter_zeros(smem_layout))\n        ),\n    )\n    return smem_layout_staged\n\n\n@dsl_user_op\ndef make_smem_layout_sfa(\n    tiled_mma: cute.TiledMma,\n    mma_tiler_mnk: cute.Tile,\n    sf_vec_size: int,\n    num_stages: int,\n    *,\n    loc=None,\n    ip=None,\n) -> cute.Layout:\n    \"\"\"\n    Make smem layout for SFA based on:\n\n    1. BlockScaledBasicChunk\n    2. MMA tiler shape\n    3. Scale factor vector size\n    4. Number of stages\n\n    :param tiled_mma: The tiled MMA\n    :type tiled_mma: cute.TiledMma\n    :param mma_tiler_mnk: The mma tiler shape\n    :type mma_tiler_mnk: cute.Tile\n    :param sf_vec_size: The scale factor vector size\n    :type sf_vec_size: int\n    :param num_stages: The number of stages\n    :type num_stages: int\n\n    :return: Smem layout for SFA\n    :rtype: cute.Layout\n    \"\"\"\n    # (CTA_Tile_Shape_M, MMA_Tile_Shape_K)\n    sfa_tile_shape = (\n        mma_tiler_mnk[0] // cute.size(tiled_mma.thr_id.shape),\n        mma_tiler_mnk[2],\n    )\n\n    # ((Atom_M, Rest_M),(Atom_K, Rest_K))\n    smem_layout = cute.tile_to_shape(\n        BlockScaledBasicChunk(sf_vec_size).layout,\n        sfa_tile_shape,\n        (2, 1),\n    )\n\n    mma_tile_inst_k = 4\n    # (CTA_Tile_Shape_M, MMA_Inst_Shape_K)\n    sfa_tile_shape = cute.shape_div(sfa_tile_shape, (1, mma_tile_inst_k))\n    # ((Atom_Inst_M, Atom_Inst_K), MMA_M, MMA_K))\n    smem_layout = cute.tiled_divide(smem_layout, sfa_tile_shape)\n\n    atom_m = 128\n    tiler_inst = ((atom_m, sf_vec_size),)\n    # (((Atom_Inst_M, Rest_M),(Atom_Inst_K, Rest_K)), MMA_M, MMA_K)\n    smem_layout = cute.logical_divide(smem_layout, tiler_inst)\n\n    # (((Atom_Inst_M, Rest_M),(Atom_Inst_K, Rest_K)), MMA_M, MMA_K, STAGE)\n    sfa_smem_layout_staged = cute.append(\n        smem_layout,\n        cute.make_layout(\n            num_stages, stride=cute.cosize(cute.filter_zeros(smem_layout))\n        ),\n    )\n\n    return sfa_smem_layout_staged\n\n\n@dsl_user_op\ndef make_smem_layout_sfb(\n    tiled_mma: cute.TiledMma,\n    mma_tiler_mnk: cute.Tile,\n    sf_vec_size: int,\n    num_stages: int,\n    *,\n    loc=None,\n    ip=None,\n) -> cute.Layout:\n    \"\"\"\n    Make smem layout for SFB based on:\n\n    1. BlockScaledBasicChunk\n    2. MMA tiler shape\n    3. Scale factor vector size\n    4. Number of stages\n\n    :param tiled_mma: The tiled MMA\n    :type tiled_mma: cute.TiledMma\n    :param mma_tiler_mnk: The mma tiler shape\n    :type mma_tiler_mnk: cute.Tile\n    :param sf_vec_size: The scale factor vector size\n    :type sf_vec_size: int\n    :param num_stages: The number of stages\n    :type num_stages: int\n\n    :return: Smem layout for SFA\n    :rtype: cute.Layout\n    \"\"\"\n    # (Round_Up(CTA_Tile_Shape_N, 128), MMA_Tile_Shape_K)\n    sfb_tile_shape = (\n        cute.round_up(mma_tiler_mnk[1], 128),\n        mma_tiler_mnk[2],\n    )\n\n    # ((Atom_N, Rest_N),(Atom_K, Rest_K))\n    smem_layout = cute.tile_to_shape(\n        BlockScaledBasicChunk(sf_vec_size).layout,\n        sfb_tile_shape,\n        (2, 1),\n    )\n\n    mma_tile_inst_k = 4\n    # (CTA_Tile_Shape_N, MMA_Inst_Shape_K)\n    sfb_tile_shape = cute.shape_div(sfb_tile_shape, (1, mma_tile_inst_k))\n    # ((Atom_Inst_N, Atom_Inst_K), MMA_N, MMA_K)\n    smem_layout = cute.tiled_divide(smem_layout, sfb_tile_shape)\n\n    atom_n = 128\n    tiler_inst = ((atom_n, sf_vec_size),)\n    # (((Atom_Inst_M, Rest_M),(Atom_Inst_K, Rest_K)), MMA_M, MMA_K)\n    smem_layout = cute.logical_divide(smem_layout, tiler_inst)\n\n    # (((Atom_Inst_M, Rest_M),(Atom_Inst_K, Rest_K)), MMA_M, MMA_K, STAGE)\n    sfb_smem_layout_staged = cute.append(\n        smem_layout,\n        cute.make_layout(\n            num_stages, stride=cute.cosize(cute.filter_zeros(smem_layout))\n        ),\n    )\n\n    return sfb_smem_layout_staged\n\n\n@dsl_user_op\ndef sm120_make_smem_layout_sfa(\n    tiled_mma: cute.TiledMma,\n    tile_shape_mnk: cute.Tile,\n    sf_vec_size: int,\n    num_stages: int,\n    *,\n    loc=None,\n    ip=None,\n) -> cute.Layout:\n    \"\"\"\n    Make smem layout for SFA based on:\n    1. BlockScaledBasicChunk\n    2. MMA tiler shape\n    3. Scale factor vector size\n    4. Number of stages\n\n    :param tiled_mma: The tiled MMA\n    :type tiled_mma: cute.TiledMma\n    :param mma_tiler_mnk: The mma tiler shape\n    :type mma_tiler_mnk: cute.Tile\n    :param sf_vec_size: The scale factor vector size\n    :type sf_vec_size: int\n    :param num_stages: The number of stages\n    :type num_stages: int\n\n    :return: Smem layout for SFA\n    :rtype: cute.Layout\n    \"\"\"\n\n    assert sf_vec_size == 16 or sf_vec_size == 32, \"sf_vec_size must be 16 or 32\"\n\n    blk_mn = 128\n    blk_sf = 4\n    blk_elems = blk_mn * blk_sf\n    mma_nsf = tiled_mma.shape_mnk[2] // sf_vec_size\n\n    mn_basic_block_shape = (32, 4)\n    mn_basic_block_stride = (16, 4)\n    k_basic_block_shape = (sf_vec_size, mma_nsf)\n    k_basic_block_stride = (0, 1)\n\n    assert tile_shape_mnk[0] % blk_mn == 0, (\n        \"tile_shape_mnk[0] must be divisible by blk_mn\"\n    )\n\n    sSFA_shapeM = (mn_basic_block_shape, tile_shape_mnk[0] // blk_mn)\n    sSF_strideM = (mn_basic_block_stride, blk_elems)\n\n    assert tile_shape_mnk[2] % (blk_sf * mma_nsf) == 0, (\n        \"tile_shape_mnk[2] must be divisible by blk_sf * mma_nsf\"\n    )\n\n    sSFA_shapeK = (\n        k_basic_block_shape,\n        blk_sf // mma_nsf,\n        tile_shape_mnk[2] // sf_vec_size // blk_sf,\n    )\n    sSF_strideK = (\n        k_basic_block_stride,\n        mma_nsf,\n        tile_shape_mnk[0] // blk_mn * blk_elems,\n    )\n\n    sSFA_shape = (sSFA_shapeM, sSFA_shapeK)\n    sSFA_stride = (sSF_strideM, sSF_strideK)\n\n    smem_layout = cute.make_layout(sSFA_shape, stride=sSFA_stride)\n\n    # (((Atom_Inst_M, Rest_M),(Atom_Inst_K, Rest_K)), MMA_M, MMA_K, STAGE)\n    sfa_smem_layout_staged = cute.append(\n        smem_layout,\n        cute.make_layout(\n            num_stages, stride=cute.cosize(cute.filter_zeros(smem_layout))\n        ),\n    )\n\n    return sfa_smem_layout_staged\n\n\n@dsl_user_op\ndef sm120_make_smem_layout_sfb(\n    tiled_mma: cute.TiledMma,\n    tile_shape_mnk: cute.Tile,\n    sf_vec_size: int,\n    num_stages: int,\n    *,\n    loc=None,\n    ip=None,\n) -> cute.Layout:\n    \"\"\"\n    Make smem layout for SFB based on:\n    1. BlockScaledBasicChunk\n    2. MMA tiler shape\n    3. Scale factor vector size\n    4. Number of stages\n\n    :param tiled_mma: The tiled MMA\n    :type tiled_mma: cute.TiledMma\n    :param mma_tiler_mnk: The mma tiler shape\n    :type mma_tiler_mnk: cute.Tile\n    :param sf_vec_size: The scale factor vector size\n    :type sf_vec_size: int\n    :param num_stages: The number of stages\n    :type num_stages: int\n\n    :return: Smem layout for SFA\n    :rtype: cute.Layout\n    \"\"\"\n\n    # A single indivisible block will hold 4 scale factors of 128 rows/columns (A/B matrix).\n    # 4 is chosen to make consecutive 32bits of data to have scale factors for only a single row(col).\n    blk_mn = 128\n    blk_sf = 4\n    blk_elems = blk_mn * blk_sf\n\n    assert sf_vec_size == 16 or sf_vec_size == 32, \"sf_vec_size must be 16 or 32\"\n\n    assert tile_shape_mnk[1] % blk_mn == 0, (\n        \"tile_shape_mnk[1] must be divisible by blk_mn\"\n    )\n\n    assert tile_shape_mnk[2] % sf_vec_size == 0, (\n        \"tile_shape_mnk[2] must be divisible by sf_vec_size\"\n    )\n\n    mma_nsf = tiled_mma.shape_mnk[2] // sf_vec_size\n\n    mn_basic_block_shape = (32, 4)\n    mn_basic_block_stride = (16, 4)\n    k_basic_block_shape = (sf_vec_size, mma_nsf)\n    k_basic_block_stride = (0, 1)\n\n    assert tile_shape_mnk[1] % blk_mn == 0, (\n        \"tile_shape_mnk[1] must be divisible by blk_mn\"\n    )\n\n    sSFA_shapeN = (mn_basic_block_shape, tile_shape_mnk[1] // blk_mn)\n    sSF_strideN = (mn_basic_block_stride, blk_elems)\n\n    assert tile_shape_mnk[2] % (blk_sf * mma_nsf) == 0, (\n        \"tile_shape_mnk[2] must be divisible by blk_sf * mma_nsf\"\n    )\n\n    sSFA_shapeK = (\n        k_basic_block_shape,\n        blk_sf // mma_nsf,\n        tile_shape_mnk[2] // sf_vec_size // blk_sf,\n    )\n    sSF_strideK = (\n        k_basic_block_stride,\n        mma_nsf,\n        tile_shape_mnk[1] // blk_mn * blk_elems,\n    )\n\n    sSFA_shape = (sSFA_shapeN, sSFA_shapeK)\n    sSFA_stride = (sSF_strideN, sSF_strideK)\n\n    smem_layout = cute.make_layout(sSFA_shape, stride=sSFA_stride)\n\n    # (((Atom_Inst_M, Rest_M),(Atom_Inst_K, Rest_K)), MMA_M, MMA_K, STAGE)\n    sfb_smem_layout_staged = cute.append(\n        smem_layout,\n        cute.make_layout(\n            num_stages, stride=cute.cosize(cute.filter_zeros(smem_layout))\n        ),\n    )\n\n    return sfb_smem_layout_staged\n\n\n@dsl_user_op\ndef make_tmem_layout_sfa(\n    tiled_mma: cute.TiledMma,\n    mma_tiler_mnk: cute.Tile,\n    sf_vec_size: int,\n    smem_layout: cute.Layout,\n    *,\n    loc=None,\n    ip=None,\n) -> cute.Layout:\n    \"\"\"Make tmem layout for SFA based on:\n\n    1. SFA smem layout per stage\n    2. Cta tile shape m\n    3. tiled MMA atom thr size\n    4. Scale factor vector size\n\n    :param tiled_mma: The tiled MMA\n    :type tiled_mma: cute.TiledMma\n    :param mma_tiler_mnk: The mma tiler shape\n    :type mma_tiler_mnk: cute.Tile\n    :param sf_vec_size: The scale factor vector size\n    :type sf_vec_size: int\n    :param smem_layout: The smem layout of SFA per stage\n    :type smem_layout: cute.Layout\n\n    :return: TMEM layout for SFA\n    :rtype: cute.Layout\n    \"\"\"\n    atom_thr_size = cute.size(tiled_mma.thr_id.shape, loc=loc, ip=ip)\n    cta_tile_shape_m = mma_tiler_mnk[0] // atom_thr_size\n\n    sfa_layout_ty = _cute_nvgpu_ir.make_tmem_layout_sfa(\n        smem_layout, cta_tile_shape_m, atom_thr_size, sf_vec_size\n    )\n    return _cute_ir.static(sfa_layout_ty, loc=loc, ip=ip)\n\n\n@dsl_user_op\ndef make_tmem_layout_sfb(\n    tiled_mma: cute.TiledMma,\n    mma_tiler_mnk: cute.Tile,\n    sf_vec_size: int,\n    smem_layout: cute.Layout,\n    *,\n    loc=None,\n    ip=None,\n) -> cute.Layout:\n    \"\"\"Make tmem layout for SFB based on:\n\n    1. SFB smem layout per stage\n    2. Cta tile shape m\n    3. tiled MMA atom thr size\n    4. Scale factor vector size\n\n    :param tiled_mma: The tiled MMA\n    :type tiled_mma: cute.TiledMma\n    :param mma_tiler_mnk: The mma tiler shape\n    :type mma_tiler_mnk: cute.Tile\n    :param sf_vec_size: The scale factor vector size\n    :type sf_vec_size: int\n    :param smem_layout: The smem layout of SFB per stage\n    :type smem_layout: cute.Layout\n\n    :return: TMEM layout for SFB\n    :rtype: cute.Layout\n    \"\"\"\n    atom_thr_size = cute.size(tiled_mma.thr_id.shape, loc=loc, ip=ip)\n    cta_tile_shape_m = mma_tiler_mnk[0] // atom_thr_size\n\n    sfb_layout_ty = _cute_nvgpu_ir.make_tmem_layout_sfb(\n        smem_layout, cta_tile_shape_m, atom_thr_size, sf_vec_size\n    )\n    return _cute_ir.static(sfb_layout_ty, loc=loc, ip=ip)\n",
  "type": "source"
}